{
    "name": "pkcs11-helper",
    "buildsystem": "autotools",
    "sources": [
        {
            "type": "archive",
            "url": "https://github.com/OpenSC/pkcs11-helper/archive/refs/tags/pkcs11-helper-1.31.0.tar.gz",
            "sha256": "585e0347892bdf45220b080c9eae9216b461f96369c19be1e4bb6d80a078dc6b",
            "x-checker-data": {
                "type": "anitya",
                "project-id": 91990,
                "stable-only": true,
                "url-template": "https://github.com/OpenSC/pkcs11-helper/archive/refs/tags/pkcs11-helper-$version.tar.gz"
            }
        },
        {
            "type": "script",
            "dest-filename": "autogen.sh",
            "commands": [
                "autoreconf -vfi"
            ]
        }
    ]
}
